editrcs/__init__.py
editrcs-0.5.3.dist-info/LICENSE.txt
editrcs-0.5.3.dist-info/METADATA
editrcs-0.5.3.dist-info/WHEEL
editrcs-0.5.3.dist-info/top_level.txt
editrcs-0.5.3.dist-info/RECORD
