Metadata-Version: 2.1
Name: editrcs
Version: 0.5.3
Summary: Library to read, manipulate and write RCS files.
Home-page: https://github.com/ben-cohen/editrcs
Author: Ben Cohen
License: GPLv3+
Platform: UNKNOWN
Classifier: Development Status :: 4 - Beta
Classifier: Environment :: Console
Classifier: Intended Audience :: Developers
Classifier: License :: OSI Approved :: GNU General Public License v3 or later (GPLv3+)
Classifier: Natural Language :: English
Classifier: Operating System :: POSIX
Classifier: Operating System :: POSIX :: Linux
Classifier: Operating System :: Unix
Classifier: Programming Language :: Python
Classifier: Topic :: Software Development :: Version Control :: CVS
Classifier: Topic :: Software Development :: Version Control :: RCS
Requires-Python: >=2.7
License-File: LICENSE.txt
